[
 {
   "index": 0,
   "artistName": "Michele Caliani",
   "image": "https://lh3.googleusercontent.com/aVb0MtP7z5XRn34sVCrm7_ZOCCiD0NLvgK1BGWWEKuYqT0LdzTFIovJRlgJWfu9tfBF41MIXSHuPpm7gNPXwoVHHPd59QYXG3lxRWvQcQywY1VrguUOzGNbvfeDF_tGzlxKb49vihQ=w2400",
   "imageURL": "https://unsplash.com/photos/iLAAT1E-H_8",
   "media": "https://unsplash.com/@michele00caliani",
   "dimensions": "2270 x 4164",
   "published": "January 7, 2020",
   "tag1": "blacks",
   "tag2": "whites",
   "tag3": "models",
   "tag4": "womans",
   "tag5": "darks",
   "tag6": "dark backgrounds",
   "tag7": "black and white",
   "tag8": "",
   "tag9": "",
   "tag10": ""
 },
 {
   "index": 1,
   "artistName": "Tom Barrett",
   "image": "https://lh3.googleusercontent.com/GtGhhxbP-3lDFuPOF6t4xm8YLyqAE79N76TIaohKZCdyorrGlxN8vnEg_Y-P-2cOSPVY2n_3VlHX7O0dxPLVwBPAxm4t9TwddnOybJVR1AkeHDS2EVlpQkoTyi_y6aC2FRQsiO_mYw=w2400",
   "imageURL": "https://unsplash.com/photos/2t60-JYQ5pk",
   "media": "https://www.instagram.com/wistomsin/",
   "dimensions": "4000 × 6000",
   "published": "August 20, 2017",
   "tag1": "blacks",
   "tag2": "whites",
   "tag3": "black and white",
   "tag4": "sky",
   "tag5": "clouds",
   "tag6": "darks",
   "tag7": "aerials",
   "tag8": "",
   "tag9": "",
   "tag10": ""
 },
 {
   "index": 2,
   "artistName": "Hoach Le Dinh",
   "image": "https://lh3.googleusercontent.com/u6hbzOcZrX2ncN97Vul4n5DzUOA5MRMQUQRGSKjRpPVTFUytjlMHLnifSwZNQaqsUMQZ5BgJxvaMgyOYN6ZzK60IL26i6kUM0nztWBnRUutDeSgoqrCDVfa1x4g94MHS9VfYZk8TJw=w2400",
   "imageURL": "https://unsplash.com/photos/5DJqsjAYlmk",
   "media": "https://hoachld.com",
   "dimensions": "4000 × 6000",
   "published": "May 28, 2016",
   "tag1": "blacks",
   "tag2": "whites",
   "tag3": "black and white",
   "tag4": "docks",
   "tag5": "waters",
   "tag6": "darks",
   "tag7": "dark backgrounds",
   "tag8": "brokens",
   "tag9": "",
   "tag10": ""
 },
 {
   "index": 3,
   "artistName": "Osman Rana",
   "image": "https://lh3.googleusercontent.com/oBCvcGLUA1uS2GSLAqLa2EXzUVK1trommSxb7n3qhS9X8VAaTGckmaW0f8qwh4K6E5-tJM48FU2spL_HBUT1ftOpo6OweTTRdIuvOnJGEaloS7jAdaQXE7Iud8LXUkVLlk7nhr_nPA=w2400",
   "imageURL": "https://unsplash.com/photos/dI9KhXi0ooE",
   "media": "https://www.oranaphotography.com",
   "dimensions": "2185 × 3059",
   "published": "June 24, 2017",
   "tag1": "blacks",
   "tag2": "whites",
   "tag3": "black and white",
   "tag4": "buildings",
   "tag5": "new york city",
   "tag6": "architectures",
   "tag7": "side view",
   "tag8": "empire state building",
   "tag9": "",
   "tag10": ""
 },
 {
   "index": 4,
   "artistName": "Pipe A.",
   "image": "https://lh3.googleusercontent.com/WpItRKGtOMoif4boJvI8gBWknw-YYnHqckCLdYQMecVnomePFN_IiWGYvPzoPnM06qsk4KSPPXLimMW0S3y3sl3XNZNj7eAnM3iC5Zk-d8Z-iZhzqiUqzMtqf13HJGUARy75HJv0GQ=w2400",
   "imageURL": "https://unsplash.com/photos/WQTwsgq_mxg",
   "media": "https://unsplash.com/@pipeaguileram",
   "dimensions": "1638 × 2048",
   "published": "May 14, 2017",
   "tag1": "blacks",
   "tag2": "whites",
   "tag3": "black and white",
   "tag4": "buildings",
   "tag5": "new york city",
   "tag6": "architectures",
   "tag7": "aerial views",
   "tag8": "aerials",
   "tag9": "top views",
   "tag10": "tops"
 },
 {
   "index": 5,
   "artistName": "Sven Brandsma",
   "image": "https://lh3.googleusercontent.com/bXk9F6TrXKUZFEvwOLbrYntt32L7dv8qp-vMeV--cwysvD3eQY33LFfBCoMVArE3Qp2AoggFtmHn09E1MVNTwQjPLJQKXgkGQ1_sRX-fYP_0W0PuVmJVYTsPhMwhRA4uzFgB-CPrdA=w2400",
   "imageURL": "https://unsplash.com/photos/ZvO9hqVE62s",
   "media": "https://unsplash.com/@seffen99",
   "dimensions": "2176 × 3264",
   "published": "November 9, 2019",
   "tag1": "blacks",
   "tag2": "whites",
   "tag3": "black and white",
   "tag4": "trees",
   "tag5": "darks",
   "tag6": "dark backgrounds",
   "tag7": "nights",
   "tag8": "woods",
   "tag9": "",
   "tag10": ""
 },
 {
   "index": 6,
   "artistName": "Esteban Amaro",
   "image": "https://lh3.googleusercontent.com/MYsoJ94jMLH8DUvZMNa02Yl41pHszzK81FvkJJhA_VHua4Z-QyLvR9M7bzviIUzbBQ3jXqLRoBsSafQU-OrNZbj4JRkf-3QBP1kH5zRT79JFZF6TS4wNsMgOFVcM_Ic4N3mllX7Mwg=w2400",
   "imageURL": "https://unsplash.com/photos/hy8y0Wp_Lp0",
   "media": "https://www.instagram.com/amaro777/",
   "dimensions": "4000 × 6016",
   "published": "October 14, 2019",
   "tag1": "blacks",
   "tag2": "whites",
   "tag3": "black and white",
   "tag4": "waters",
   "tag5": "birds",
   "tag6": "side view",
   "tag7": "boats",
   "tag8": "docks",
   "tag9": "horizons",
   "tag10": "light backgrounds"
 },
 {
   "index": 7,
   "artistName": "Lilian Pereir",
   "image": "https://lh3.googleusercontent.com/FdjIZtqFFKx-mLFTWK--I9C2g0mp--UgssK-54dNqLDMc9ziWVEWn6Ae6pyXj49vHx4tdktKNXsqap_kwiQaOGwwkmwq4D3p5KusIaCLN8ZYdsF17e0fi5ZMzoUtKu3R21qEJIit9w=w2400",
   "imageURL": "https://unsplash.com/photos/tHHoR5oJyY4",
   "media": "https://unsplash.com/@lilianpereir",
   "dimensions": "3456 × 4723",
   "published": "June 19, 2018",
   "tag1": "blacks",
   "tag2": "whites",
   "tag3": "black and white",
   "tag4": "womans",
   "tag5": "models",
   "tag6": "lightings",
   "tag7": "artistic",
   "tag8": "",
   "tag9": "",
   "tag10": ""
 },
 {
   "index": 8,
   "artistName": "Kylie De Guia",
   "image": "https://lh3.googleusercontent.com/uu_uKwA5YPGlAe29ulClHs1adxL37D_rVU0Coam2uCuROhs4D5MEeGjPfZXYnHkADb3OJJ2sBC0wiG78ad1PTr2jwRGYpEIc-BjUXQbAyckXbhdHUwCSRBh3b_kEFVy8-XJpxu8mZA=w2400",
   "imageURL": "https://unsplash.com/photos/2g16XHvL0gI",
   "media": "https://unsplash.com/@captured_deguia",
   "dimensions": "1937 × 2583",
   "published": "November 5, 2019",
   "tag1": "blacks",
   "tag2": "whites",
   "tag3": "black and white",
   "tag4": "parks",
   "tag5": "amusements",
   "tag6": "amusement parks",
   "tag7": "ferris wheels",
   "tag8": "wheels",
   "tag9": "light backgrounds",
   "tag10": "lightings"
 },
 {
   "index": 9,
   "artistName": "Marcel Karg",
   "image": "https://lh3.googleusercontent.com/I4cJzld7I-seBy0FS-4EyJmqWzaPUEJMYPH_AFfBqKSUHg8EIHGEoJhQkPRa4hXMF8--qQdCFPqdpA0ggAe5lz0Yy5bRisVCmdQbSqA8FIsgO7c-JJKBndmyzYTnI4AYtf0XrYOIJg=w2400",
   "imageURL": "https://unsplash.com/photos/wxv2Rxcdpqc",
   "media": "https://www.instagram.com/immarcey/",
   "dimensions": "3375 × 6000",
   "published": "November 20, 2020",
   "tag1": "blacks",
   "tag2": "whites",
   "tag3": "black and white",
   "tag4": "architectures",
   "tag5": "buildings",
   "tag6": "light backgrounds",
   "tag7": "lightings",
   "tag8": "",
   "tag9": "",
   "tag10": ""
 },
 {
   "index": 10,
   "artistName": "Daniele D'Andreti",
   "image": "https://lh3.googleusercontent.com/nmX6zhojfzZI2VsaOuB_zirb2QSuwoKGj_i3Ee1PHyEM9DyftI8CmEOKej2z4-eVHexNmLoYQivADR_DXgs725mTyQXnCO7lvwkNctEMh_qEO6RliLRJZnrcjJJXlI6Q2CXyquKRiQ=w2400",
   "imageURL": "https://unsplash.com/photos/jQ49DUhffos",
   "media": "https://www.thestar.it",
   "dimensions": "2912 × 4368",
   "published": "January 21, 2019",
   "tag1": "blacks",
   "tag2": "whites",
   "tag3": "black and white",
   "tag4": "models",
   "tag5": "angels",
   "tag6": "religions",
   "tag7": "sculptures",
   "tag8": "artistics",
   "tag9": "",
   "tag10": ""
 },
 {
   "index": 11,
   "artistName": "Shifaaz shamoon",
   "image": "https://lh3.googleusercontent.com/lV3dIzZgWnJsNzNvYBszw8JKvB0k8FFV8tvMjUMFt1WzYcU3Rqm8-u1cPssPH6wzhe80ByHMYgKEoWarDS9boGjuYNE476xrtHV69-IE9vc8QOck-FGk8VWdkVTe98vbi8oW_HwEig=w2400",
   "imageURL": "https://unsplash.com/photos/pNrMhpntZFM",
   "media": "https://www.instagram.com/sotti/",
   "dimensions": "3505 × 5257",
   "published": "July 2, 2017",
   "tag1": "blacks",
   "tag2": "whites",
   "tag3": "black and white",
   "tag4": "models",
   "tag5": "woman",
   "tag6": "women",
   "tag7": "beaches",
   "tag8": "waters",
   "tag9": "light backgrounds",
   "tag10": "lightings"
 },
 {
   "index": 12,
   "artistName": "Tommaso Prinetti",
   "image": "https://lh3.googleusercontent.com/r1z3YrvNCSLsAxSr9Zqy-i3wwCn56ISBK24ZMciy-WwvhhTtcWP65T-WxqQMsHmm1uOcpB2CUdwRVe6-uhhoXYOLuoMAFMbbrYRVGTqQwxAA7gBOWlT1hOrWN9XESZz4527BIyjcDQ=w2400",
   "imageURL": "https://unsplash.com/photos/7qIEOwPmnnk",
   "media": "https://unsplash.com/@costhanzo_cloro",
   "dimensions": "4000 × 6000",
   "published": "December 26, 2019",
   "tag1": "blacks",
   "tag2": "whites",
   "tag3": "black and white",
   "tag4": "sculptures",
   "tag5": "man",
   "tag6": "men",
   "tag7": "animals",
   "tag8": "dogs",
   "tag9": "",
   "tag10": ""
 },
 {
   "index": 13,
   "artistName": "Timothy Perry",
   "image": "https://lh3.googleusercontent.com/RrtwTPZp45ubPEkQPQW_fkNAJL9dsoxwAAsNkhNYGeKuldOhB4qn_FazMjWKYJAvTCEF9gmprJt0LtriCKRhZNStb6B3RL8Z6s8uycSDE_i8NRbVU4C1rcpuLUeF9Nvw0XDrtT4ixA=w2400",
   "imageURL": "https://unsplash.com/photos/JQUmju2SMxE",
   "media": "https://unsplash.com/@thjperry",
   "dimensions": "7768 × 11648",
   "published": "August 8, 2019",
   "tag1": "blacks",
   "tag2": "whites",
   "tag3": "black and white",
   "tag4": "models",
   "tag5": "man",
   "tag6": "men",
   "tag7": "darks",
   "tag8": "dark backgrounds",
   "tag9": "lightings",
   "tag10": ""
 },
 {
   "index": 14,
   "artistName": "Sourav Maji",
   "image": "https://lh3.googleusercontent.com/b4ZmC_i3L1pG_k40_yj90X_QkF5fdgKON41jJ03BdmVVN5w3d0v3w5GenDoFVhlPHxTXeel_ElRNguwnBvQs4DrHSCDyU_ItO1C6v5iZXVGdfaTjsoVREVd8NnBNa7A3Ej-kYS4sLw=w2400",
   "imageURL": "https://unsplash.com/photos/IHYEzb0ZzXQ",
   "media": "https://unsplash.com/@dream_shots",
   "dimensions": "2653 × 3887",
   "published": "June 28, 2019",
   "tag1": "blacks",
   "tag2": "whites",
   "tag3": "black and white",
   "tag4": "watches",
   "tag5": "times",
   "tag6": "clocks",
   "tag7": "timepieces",
   "tag8": "hands",
   "tag9": "",
   "tag10": ""
 },
 {
   "index": 15,
   "artistName": "Mitchell Luo",
   "image": "https://lh3.googleusercontent.com/kABowNZC5En7TEC_s8JGthgMCtqr8tyghnv2eBy3CNA-eoQFFpbcVkVIEJywJDKZmAngJk7CwkuLHo9hmANq-oX2ruD5cMsT0BINDNStrY-MgG17Bz2Q_CZI3ZdOV6amS_OkoTqP7Q=w2400",
   "imageURL": "https://unsplash.com/photos/istYOcfaY6U",
   "media": "https://mitchelll.com",
   "dimensions": "4000 × 6000",
   "published": "December 20, 2019",
   "tag1": "blacks",
   "tag2": "whites",
   "tag3": "black and white",
   "tag4": "architectures",
   "tag5": "abstractions",
   "tag6": "abstracts",
   "tag7": "artistic",
   "tag8": "buildings",
   "tag9": "",
   "tag10": ""
 },
 {
   "index": 16,
   "artistName": "T. Kaiser",
   "image": "https://lh3.googleusercontent.com/oDYnAFtuOqrDjbkxfFhX5MkrzUjn4vROcVAln3BE2mxIBD-hQXr0PalUugo-ITzAig04ZwlzMHMRqD6jtAu812dscZT2Yw_zgL4XcUsJ4FAhA6zqZZDNtlk-_b_B3UkonChnIcUhkg=w2400",
   "imageURL": "https://unsplash.com/photos/9xFCHrQxzlY",
   "media": "https://www.instagram.com/ka_is_er/",
   "dimensions": "3456 × 5184",
   "published": "October 13, 2020",
   "tag1": "blacks",
   "tag2": "whites",
   "tag3": "black and white",
   "tag4": "models",
   "tag5": "man",
   "tag6": "men",
   "tag7": "darks",
   "tag8": "dark backgrounds",
   "tag9": "lightings",
   "tag10": ""
 },
 {
   "index": 17,
   "artistName": "Ria Alfana",
   "image": "https://lh3.googleusercontent.com/58K9UYLG9S0uQMtZNhjpvv5DWqmy2zjf6NVmYECeLyTzi7hKBnC85hYA6bmx88cbK7FZKcFYfEPornI142cxLLoK4mVm7C9_TMdbekkaW9ojtTwNSN022T8oRuMyilPG4t_-aAaVGQ=w2400",
   "imageURL": "https://unsplash.com/photos/uE5ZT4cHsjw",
   "media": "https://unsplash.com/@ria_alfana",
   "dimensions": "3282 × 5848",
   "published": "June 28, 2019",
   "tag1": "blacks",
   "tag2": "whites",
   "tag3": "black and white",
   "tag4": "animals",
   "tag5": "cats",
   "tag6": "lightings",
   "tag7": "light backgrounds",
   "tag8": "cute",
   "tag9": "",
   "tag10": ""
 },
 {
   "index": 18,
   "artistName": "the blowup",
   "image": "https://lh3.googleusercontent.com/d6_cP7skdwll4FLWDUNEtTB_Zx2r2Xt3WnwLigkttxmlJn1Q0ZsNscRt9leT3fqYWpu3Nl2YMpAF4potgFj0EQ_xRTw191EPIVBl-Tj6OYBCRd1FD1rFvaqqsz4bZ3Ng2P_b24_LPA=w2400",
   "imageURL": "https://unsplash.com/photos/lqdnx9O8R-s",
   "media": "https://www.instagram.com/theblowupphoto/",
   "dimensions": "2352 × 3136",
   "published": "November 20, 2020",
   "tag1": "blacks",
   "tag2": "whites",
   "tag3": "black and white",
   "tag4": "animals",
   "tag5": "birds",
   "tag6": "swans",
   "tag7": "waters",
   "tag8": "silhouettes",
   "tag9": "lightings",
   "tag10": ""
 },
 {
   "index": 19,
   "artistName": "Vishwasa Navada K",
   "image": "https://lh3.googleusercontent.com/hi2FWWCB2DDli-NG_73h6F00lIgd278VTqg4Mri2nAxfrdHKM7rJDUJ31izA_RYeobjqIFnrkHILNQFAlFWwbbX4T83nSm-q8YAS7pJcf-OLXcVtOCI8r2T-Qsf8vGyssZ6_Yb5VTg=w2400",
   "imageURL": "https://unsplash.com/photos/XBUv9z36pPA",
   "media": "https://vishwas.tech",
   "dimensions": "3000 × 4000",
   "published": "June 23, 2020",
   "tag1": "blacks",
   "tag2": "whites",
   "tag3": "black and white",
   "tag4": "buildings",
   "tag5": "architectures",
   "tag6": "lightings",
   "tag7": "bottom views",
   "tag8": "artistics",
   "tag9": "",
   "tag10": ""
 },
 {
   "index": 20,
   "artistName": "Joshua Freake",
   "image": "https://lh3.googleusercontent.com/YVSrnF27PmOdmBMVeKY9ikfZgIrqub7Yd5O3rwF1VdvxONuQyLvpsLFnzn6KCFYqF-fGjUELoCxmf82Y5vwDd1rXWk_24zClP5PU7ZpLi0ZtSKw4NIIDDFc1oalm-wzkYaPyELbaow=w2400",
   "imageURL": "https://unsplash.com/photos/KHGZn-fwsdo",
   "media": "https://unsplash.com/@joshfreake",
   "dimensions": "4000 × 6000",
   "published": "September 21, 2019",
   "tag1": "blacks",
   "tag2": "whites",
   "tag3": "black and white",
   "tag4": "architectures",
   "tag5": "buildings",
   "tag6": "lightings",
   "tag7": "nights",
   "tag8": "darks",
   "tag9": "dark backgrounds",
   "tag10": "city"
 },
 {
   "index": 21,
   "artistName": "Nick Rickert",
   "image": "https://lh3.googleusercontent.com/0-z6EIfv8IWGGdUl_I9V_Y_dwkI2RsGqGMkeLhdxONDpFJxy6Yc2VW_8C7yr_d5NJuq7X7ShAwqDkzwe2Q93KV6V5h-tUwFBjN9CnO-lTSueW_uKIkQhKwGN1vIG7cALP3W0FTTCMw=w2400",
   "imageURL": "https://unsplash.com/photos/k89oHnnOoUQ",
   "media": "https://www.instagram.com/nick_rickert/",
   "dimensions": "3840 × 4800",
   "published": "September 21, 2020",
   "tag1": "blacks",
   "tag2": "whites",
   "tag3": "black and white",
   "tag4": "natures",
   "tag5": "trees",
   "tag6": "mountains",
   "tag7": "views",
   "tag8": "outdoors",
   "tag9": "",
   "tag10": ""
 },
 {
   "index": 22,
   "artistName": "Hennie Stander",
   "image": "https://lh3.googleusercontent.com/9Ybhqvenp-Sn-HU2lcU-6nVs5CUdV_5Nih5CvbbNVh1OGbmZrxZtRv49ejYymN4Hr0VJFYEOOcksDk7PuxIvFDiUo3dDnSRL0FbVMvbT36AB_zroR3n8rIcQ6BgzfbQxyJYkXOhGDw=w2400",
   "imageURL": "https://unsplash.com/photos/8E5HawfqCMM",
   "media": "https://hstander7.wixsite.com/someofhennieswork",
   "dimensions": "7087 × 10630",
   "published": "November 23, 2020",
   "tag1": "blacks",
   "tag2": "whites",
   "tag3": "black and white",
   "tag4": "natures",
   "tag5": "trees",
   "tag6": "lightings",
   "tag7": "light backgrounds",
   "tag8": "outdoors",
   "tag9": "",
   "tag10": ""
 },
 {
   "index": 23,
   "artistName": "Sergio Martínez",
   "image": "https://lh3.googleusercontent.com/QyyeBLuTdmPnBOZl8D_G_xvBLQVQC1g_QmbdjaReW3M0OA3fI-E31d3Z3mpw1-iP9PQIhfPRcxJe-OuIwRGuIZPYppAt-SKSC87SJZyMtLHzTeXLbkhB6GCzRN7YjDNLqwpVW2mn0w=w2400",
   "imageURL": "https://unsplash.com/photos/ISTnQlYPXL4",
   "media": "https://www.instagram.com/azerigrisa/",
   "dimensions": "2960 × 3946",
   "published": "December 5, 2020",
   "tag1": "blacks",
   "tag2": "whites",
   "tag3": "black and white",
   "tag4": "architectures",
   "tag5": "buildings",
   "tag6": "walking",
   "tag7": "woman",
   "tag8": "sidewalks",
   "tag9": "city",
   "tag10": ""
 },
 {
   "index": 24,
   "artistName": "the blowup",
   "image": "https://lh3.googleusercontent.com/wBC0f2SqRKU-kDqmGw_E55q3kFXMdRnFcqz4jgiWVEWnIYGAB0IWvdtOarrz5TF4WWlLEns12OvqK874o8NWaJyxKI6jqL7U_BUjPG8cAHOm8pf8m9YGWiSE93b1q1y60wILhfS08w=w2400",
   "imageURL": "https://unsplash.com/photos/mOqy808g5G8",
   "media": "https://www.instagram.com/theblowupphoto/",
   "dimensions": "2186 × 2914",
   "published": "September 18, 2020",
   "tag1": "blacks",
   "tag2": "whites",
   "tag3": "black and white",
   "tag4": "flags",
   "tag5": "united kingdom",
   "tag6": "england",
   "tag7": "uk",
   "tag8": "dark backgrounds",
   "tag9": "lightings",
   "tag10": "patriots"
 },
 {
   "index": 25,
   "artistName": "Sebastián Ramírez Sánchez",
   "image": "https://lh3.googleusercontent.com/_PaB04uDYGh91p_Jxf8b8-qRs18Nyh7rtgSmI7Kz_brDIqZj5EGGgMzHFjCu6dj3fzypMmnAsVKVeifYwdc-qXckdtkTXd0MvY_iDwR5qAvP2YRLCEvCStzQQplh34jhseVxxkVU6w=w2400",
   "imageURL": "https://unsplash.com/photos/6t4_WmFVVpY",
   "media": "https://www.instagram.com/randlx/",
   "dimensions": "2448 × 3264",
   "published": "November 10, 2020",
   "tag1": "blacks",
   "tag2": "whites",
   "tag3": "black and white",
   "tag4": "beaches",
   "tag5": "waters",
   "tag6": "oceans",
   "tag7": "rocks",
   "tag8": "lightings",
   "tag9": "summers",
   "tag10": "sunlights"
 },
 {
   "index": 26,
   "artistName": "Michael C",
   "image": "https://lh3.googleusercontent.com/4TqYz8TBRSW7pv6oaGSv4LQ5tAWIWRCVQxUoJlhd3PcZIez8KRv8a3VoKNoJKnOiKqfqsR-hx7LNWMGnZoVQIHbKTZbtWwdQfF3wzBWoBr6GKxsNEXYSYCv-3SAavU_tUD5KYMcF0g=w2400",
   "imageURL": "https://unsplash.com/photos/pMWECyRaZLE",
   "media": "https://unsplash.com/@michealcopley03",
   "dimensions": "2894 × 4607",
   "published": "September 20, 2020",
   "tag1": "blacks",
   "tag2": "whites",
   "tag3": "black and white",
   "tag4": "checkered",
   "tag5": "textile",
   "tag6": "artistics",
   "tag7": "designs",
   "tag8": "",
   "tag9": "",
   "tag10": ""
 },
 {
   "index": 27,
   "artistName": "Jose Rose",
   "image": "https://lh3.googleusercontent.com/UbZeddu0QD9_ymEvGqQX0Lw80zyN9q2_KUYO5CiiO911V89_lSCwAfnzAG94s-iGnh4-mt59kReJGsqVNSW0FmI0_IjmEU8hcRHwneIURL-crinXfrvn-8pfUmUtvEzYGXZsONHIqA=w2400",
   "imageURL": "https://unsplash.com/photos/trYl7JYATH0",
   "media": "https://www.joshrose.photography",
   "dimensions": "3992 × 5976",
   "published": "January 9, 2018",
   "tag1": "blacks",
   "tag2": "whites",
   "tag3": "black and white",
   "tag4": "abstractions",
   "tag5": "abstracts",
   "tag6": "artistics",
   "tag7": "designs",
   "tag8": "darks",
   "tag9": "dark backgrounds",
   "tag10": ""
 },
 {
   "index": 28,
   "artistName": "Daniel Olah",
   "image": "https://lh3.googleusercontent.com/OFQiTUSTYOFobIv5xUg-fKUhP4F3k8cvo-h7sQMekI6gnTqCMvLE2CouISMCIZT3JM4_5eL96rJI8IhMLbmi0545bNWEJU87WosFAdpztYdmd51CZ_rdi09RojNk9S2pE2kz8JWwNg=w2400",
   "imageURL": "https://unsplash.com/photos/2cHW5TKr9Vs",
   "media": "https://www.instagram.com/danesduet/",
   "dimensions": "3166 × 4607",
   "published": "October 31, 2017",
   "tag1": "blacks",
   "tag2": "whites",
   "tag3": "black and white",
   "tag4": "tracks",
   "tag5": "track and field",
   "tag6": "artistics",
   "tag7": "athletes",
   "tag8": "athletics",
   "tag9": "darks",
   "tag10": ""
 },
 {
   "index": 29,
   "artistName": "Mike Ko",
   "image": "https://lh3.googleusercontent.com/Ae5qVdGEyBzh4akJhP16N-2GTKvYOT8GoBlCrMd2JfNsPi8LIh9AJgquAYNBdL8CAy1glXRh_VaLcISTkWGiIuzV-4qNBpKVpZQLztDFzSFkO44U6oqz4wcZMucdDEWjee-Qa2W3tQ=w2400",
   "imageURL": "https://unsplash.com/photos/tjod6u2RpiU",
   "media": "https://unsplash.com/photos/tjod6u2RpiU",
   "dimensions": "3840 × 5760",
   "published": "December 11, 2015",
   "tag1": "blacks",
   "tag2": "whites",
   "tag3": "black and white",
   "tag4": "snows",
   "tag5": "winters",
   "tag6": "abstractions",
   "tag7": "abstracts",
   "tag8": "artistics",
   "tag9": "darks",
   "tag10": "lightings"
 },
 {
   "index": 30,
   "artistName": "Mads Schmidt Rasmussen",
   "image": "https://lh3.googleusercontent.com/7JEQeMITSL0vjVDAjgj5hCVfy8P4iEQlMDvXfK8k5B5dSpuOvHkH6f6gngPfSwY0zRFUfjHlzqdaGguDVn2RaR0G1mz65AZ2HZB52ulyuiJSLIa0MpndQXvv_traT_qZTef1zUjPWA=w2400",
   "imageURL": "https://unsplash.com/photos/6YmzwamGzCg",
   "media": "https://www.instagram.com/immvds/",
   "dimensions": "3556 × 4741",
   "published": "February 20, 2018",
   "tag1": "blacks",
   "tag2": "whites",
   "tag3": "black and white",
   "tag4": "greys",
   "tag5": "forests",
   "tag6": "natures",
   "tag7": "aerials",
   "tag8": "aerial views",
   "tag9": "fogs",
   "tag10": "lightings"
 },
 {
   "index": 31,
   "artistName": "Fabrice Villard",
   "image": "https://lh3.googleusercontent.com/6w8LKKRFo11KP1odXv8czjw3QGeb4r04ZBXESIGwIk1DIhITko1kVkw9kip4isO3W8jscHsUWd77SHMu-UFMx1CUUmLTjtgG0h14UxQD40DyXoPUCW1H1fs1glCS5oLjXEzy05vs7A=w2400",
   "imageURL": "https://unsplash.com/photos/Jrl_UQcZqOc",
   "media": "http://www.enclosed.ch",
   "dimensions": "3264 × 4896",
   "published": "March 5, 2018",
   "tag1": "blacks",
   "tag2": "whites",
   "tag3": "black and white",
   "tag4": "trees",
   "tag5": "natures",
   "tag6": "winters",
   "tag7": "lightings",
   "tag8": "side view",
   "tag9": "",
   "tag10": ""
 }
]
